{
  "scrape_time": "2026-05-18T22:50:37.088568Z",
  "signals": {
    "eurusd": {
      "signal": "unavailable",
      "confidence": 0.0,
      "direction": "neutral",
      "reason": "Pivot data unavailable",
      "pivot_state": "unavailable",
      "ema_bias": "neutral_bias",
      "ema_cross": "none",
      "macro_align": "unavailable",
      "warming_up": true,
      "ok": false,
      "ohlc_date": "",
      "pivot_source": "unavailable",
      "ema_source": "stooq_h1",
      "h1_ema_alignment": "",
      "h1_ema_direction": "",
      "pivot_direction": "",
      "h1_ema_conviction_mult": "",
      "h1_rsi": null,
      "h1_rsi_label": "",
      "h1_rsi_signal": "",
      "h1_ema": {},
      "d1_rsi": null,
      "d1_rsi_state": "unavailable",
      "d1_rsi_bias": "unavailable",
      "technical_summary": {},
      "technical_context": {},
      "h1_status": "insufficient_data",
      "h1_movement": "insufficient_data",
      "h1_bias_alignment": "neutral_or_mixed",
      "h1_ema_bias": "neutral_bias",
      "h1_score": 0,
      "h1_bars": 1,
      "h1_file": "public_html/momentum_closes.json",
      "h1_reason": "Need at least 50 completed H1 closes for EMA20/EMA50",
      "fast_ema": null,
      "slow_ema": null,
      "last_close": null,
      "trend_bias": "",
      "h1_summary": "\u2796 H1 NEUTRAL \u00b7 EMA n/a \u00b7 Close n/a \u00b7 RSI n/a",
      "h1_adjustment_text": "no change"
    },
    "gbpusd": {
      "signal": "unavailable",
      "confidence": 0.0,
      "direction": "neutral",
      "reason": "Pivot data unavailable",
      "pivot_state": "unavailable",
      "ema_bias": "neutral_bias",
      "ema_cross": "none",
      "macro_align": "unavailable",
      "warming_up": true,
      "ok": false,
      "ohlc_date": "",
      "pivot_source": "unavailable",
      "ema_source": "stooq_h1",
      "h1_ema_alignment": "",
      "h1_ema_direction": "",
      "pivot_direction": "",
      "h1_ema_conviction_mult": "",
      "h1_rsi": null,
      "h1_rsi_label": "",
      "h1_rsi_signal": "",
      "h1_ema": {},
      "d1_rsi": null,
      "d1_rsi_state": "unavailable",
      "d1_rsi_bias": "unavailable",
      "technical_summary": {},
      "technical_context": {},
      "h1_status": "insufficient_data",
      "h1_movement": "insufficient_data",
      "h1_bias_alignment": "neutral_or_mixed",
      "h1_ema_bias": "neutral_bias",
      "h1_score": 0,
      "h1_bars": 1,
      "h1_file": "public_html/momentum_closes.json",
      "h1_reason": "Need at least 50 completed H1 closes for EMA20/EMA50",
      "fast_ema": null,
      "slow_ema": null,
      "last_close": null,
      "trend_bias": "",
      "h1_summary": "\u2796 H1 NEUTRAL \u00b7 EMA n/a \u00b7 Close n/a \u00b7 RSI n/a",
      "h1_adjustment_text": "no change"
    },
    "usdjpy": {
      "signal": "unavailable",
      "confidence": 0.0,
      "direction": "neutral",
      "reason": "Pivot data unavailable",
      "pivot_state": "unavailable",
      "ema_bias": "neutral_bias",
      "ema_cross": "none",
      "macro_align": "unavailable",
      "warming_up": true,
      "ok": false,
      "ohlc_date": "",
      "pivot_source": "unavailable",
      "ema_source": "stooq_h1",
      "h1_ema_alignment": "",
      "h1_ema_direction": "",
      "pivot_direction": "",
      "h1_ema_conviction_mult": "",
      "h1_rsi": null,
      "h1_rsi_label": "",
      "h1_rsi_signal": "",
      "h1_ema": {},
      "d1_rsi": null,
      "d1_rsi_state": "unavailable",
      "d1_rsi_bias": "unavailable",
      "technical_summary": {},
      "technical_context": {},
      "h1_status": "insufficient_data",
      "h1_movement": "insufficient_data",
      "h1_bias_alignment": "neutral_or_mixed",
      "h1_ema_bias": "neutral_bias",
      "h1_score": 0,
      "h1_bars": 1,
      "h1_file": "public_html/momentum_closes.json",
      "h1_reason": "Need at least 50 completed H1 closes for EMA20/EMA50",
      "fast_ema": null,
      "slow_ema": null,
      "last_close": null,
      "trend_bias": "",
      "h1_summary": "\u2796 H1 NEUTRAL \u00b7 EMA n/a \u00b7 Close n/a \u00b7 RSI n/a",
      "h1_adjustment_text": "no change"
    },
    "xauusd": {
      "signal": "unavailable",
      "confidence": 0.0,
      "direction": "neutral",
      "reason": "Pivot data unavailable",
      "pivot_state": "unavailable",
      "ema_bias": "neutral_bias",
      "ema_cross": "none",
      "macro_align": "unavailable",
      "warming_up": true,
      "ok": false,
      "ohlc_date": "",
      "pivot_source": "unavailable",
      "ema_source": "stooq_h1",
      "h1_ema_alignment": "",
      "h1_ema_direction": "",
      "pivot_direction": "",
      "h1_ema_conviction_mult": "",
      "h1_rsi": null,
      "h1_rsi_label": "",
      "h1_rsi_signal": "",
      "h1_ema": {},
      "d1_rsi": null,
      "d1_rsi_state": "unavailable",
      "d1_rsi_bias": "unavailable",
      "technical_summary": {},
      "technical_context": {},
      "h1_status": "insufficient_data",
      "h1_movement": "insufficient_data",
      "h1_bias_alignment": "neutral_or_mixed",
      "h1_ema_bias": "neutral_bias",
      "h1_score": 0,
      "h1_bars": 1,
      "h1_file": "public_html/momentum_closes.json",
      "h1_reason": "Need at least 50 completed H1 closes for EMA20/EMA50",
      "fast_ema": null,
      "slow_ema": null,
      "last_close": null,
      "trend_bias": "",
      "h1_summary": "\u2796 H1 NEUTRAL \u00b7 EMA n/a \u00b7 Close n/a \u00b7 RSI n/a",
      "h1_adjustment_text": "no change"
    }
  }
}